.version
COPYING
COPYING.LESSER
MANIFEST.in
README.rst
setup.cfg
setup.py
localreg/__init__.py
localreg/localreg.py
localreg/metrics.py
localreg/multivariate.py
localreg/rbf.py
localreg/rbfnet.py
localreg.egg-info/PKG-INFO
localreg.egg-info/SOURCES.txt
localreg.egg-info/dependency_links.txt
localreg.egg-info/requires.txt
localreg.egg-info/top_level.txt
test/test_localreg.py
test/test_rbf.py