Metadata-Version: 2.1
Name: localreg
Version: 0.4.0
Summary: Local Polynomial Regression
Home-page: https://github.com/sigvaldm/localreg.git
Author: Sigvald Marholm
Author-email: marholm@marebakken.com
License: LGPL
Platform: UNKNOWN
Classifier: Programming Language :: Python :: 3.5
Classifier: Programming Language :: Python :: 3.6
Classifier: Programming Language :: Python :: 3.7
Classifier: Programming Language :: Python :: 3.8
Classifier: Programming Language :: Python :: 3.9
License-File: COPYING
License-File: COPYING.LESSER
